rgevolve/smeft/warsaw/__init__.py
rgevolve/smeft/warsaw/_version.py
rgevolve/smeft/warsaw/data.h5
rgevolve_smeft_warsaw-0.1.1.dist-info/licenses/LICENSE
rgevolve_smeft_warsaw-0.1.1.dist-info/METADATA
rgevolve_smeft_warsaw-0.1.1.dist-info/WHEEL
rgevolve_smeft_warsaw-0.1.1.dist-info/top_level.txt
rgevolve_smeft_warsaw-0.1.1.dist-info/RECORD
